{
  "type": "FeatureCollection",
  "features": [
    {
      "type": "Feature",
      "properties": {
        "name_he": "Old Waystation",
        "name_en": "Old Waystation",
        "category_he": "Historic site (demo)",
        "note_he": "A fictional waystation for demonstration.",
        "coord_quality": "approx"
      },
      "geometry": {
        "type": "Point",
        "coordinates": [
          -40.02,
          33.995
        ]
      }
    },
    {
      "type": "Feature",
      "properties": {
        "name_he": "Old Fort",
        "name_en": "Old Fort",
        "category_he": "Archaeology",
        "note_he": "A synthetic fort for demonstration.",
        "coord_quality": "approx"
      },
      "geometry": {
        "type": "Point",
        "coordinates": [
          -39.985,
          34.022
        ]
      }
    },
    {
      "type": "Feature",
      "properties": {
        "name_he": "Road Well",
        "name_en": "Road Well",
        "category_he": "Historic water",
        "note_he": "A fictional well.",
        "coord_quality": "approx"
      },
      "geometry": {
        "type": "Point",
        "coordinates": [
          -39.965,
          33.98
        ]
      }
    }
  ]
}
